MANIFEST.in
README.md
setup.py
./src/deepparcellation/__init__.py
./src/deepparcellation/entry.py
./src/deepparcellation/utils/__init__.py
./src/deepparcellation/utils/common_utils.py
./src/deepparcellation/utils/image_utils.py
./src/deepparcellation/utils/io_utils.py
./src/deepparcellation/weights/__init__.py
deepparcellation.egg-info/PKG-INFO
deepparcellation.egg-info/SOURCES.txt
deepparcellation.egg-info/dependency_links.txt
deepparcellation.egg-info/entry_points.txt
deepparcellation.egg-info/requires.txt
deepparcellation.egg-info/top_level.txt
src/deepparcellation/Attention3DUNet.json
src/deepparcellation/__init__.py
src/deepparcellation/entry.py
src/deepparcellation/freesurfer_LUT.txt
src/deepparcellation/utils/__init__.py
src/deepparcellation/utils/common_utils.py
src/deepparcellation/utils/image_utils.py
src/deepparcellation/utils/io_utils.py
src/deepparcellation/weights/__init__.py
src/deepparcellation/weights/weight-roi_0.h5
src/deepparcellation/weights/weight-roi_1.h5
src/deepparcellation/weights/weight-roi_10.h5
src/deepparcellation/weights/weight-roi_100.h5
src/deepparcellation/weights/weight-roi_101.h5
src/deepparcellation/weights/weight-roi_102.h5
src/deepparcellation/weights/weight-roi_103.h5
src/deepparcellation/weights/weight-roi_104.h5
src/deepparcellation/weights/weight-roi_105.h5
src/deepparcellation/weights/weight-roi_106.h5
src/deepparcellation/weights/weight-roi_107.h5
src/deepparcellation/weights/weight-roi_108.h5
src/deepparcellation/weights/weight-roi_109.h5
src/deepparcellation/weights/weight-roi_11.h5
src/deepparcellation/weights/weight-roi_110.h5
src/deepparcellation/weights/weight-roi_111.h5
src/deepparcellation/weights/weight-roi_112.h5
src/deepparcellation/weights/weight-roi_12.h5
src/deepparcellation/weights/weight-roi_13.h5
src/deepparcellation/weights/weight-roi_14.h5
src/deepparcellation/weights/weight-roi_15.h5
src/deepparcellation/weights/weight-roi_16.h5
src/deepparcellation/weights/weight-roi_17.h5
src/deepparcellation/weights/weight-roi_18.h5
src/deepparcellation/weights/weight-roi_19.h5
src/deepparcellation/weights/weight-roi_2.h5
src/deepparcellation/weights/weight-roi_20.h5
src/deepparcellation/weights/weight-roi_21.h5
