Metadata-Version: 2.1
Name: deepparcellation
Version: 1.0.34
Summary: DeepParcellation: fast and accurate brain MRI parcellation by deep learning
Home-page: https://github.com/abysslover/deepparcellation
Author: Eun-Cheon Lim
Author-email: abysslover@gmail.com
License: GPL3.0
Keywords: brain MRI parcellation tensorflow keras
Platform: UNKNOWN
Classifier: Development Status :: 5 - Production/Stable
Classifier: Environment :: Console
Classifier: Intended Audience :: Developers
Classifier: Intended Audience :: Information Technology
Classifier: Intended Audience :: Education
Classifier: Intended Audience :: Science/Research
Classifier: License :: OSI Approved :: GNU General Public License v3 (GPLv3)
Classifier: Natural Language :: English
Classifier: Operating System :: OS Independent
Classifier: Topic :: Scientific/Engineering :: Artificial Intelligence
Classifier: Topic :: Scientific/Engineering :: Image Recognition
Classifier: Topic :: Scientific/Engineering :: Image Processing
Classifier: Topic :: Scientific/Engineering :: Medical Science Apps.
Classifier: Programming Language :: Python :: 3
Requires-Python: >=3.8
